odoo9_addon_openeducat_erp-9.0.2.4.0-py2.7-nspkg.pth
odoo_addons/openeducat_erp/__openerp__.py
odoo_addons/openeducat_erp/__init__.py
odoo_addons/openeducat_erp/doc/changelog.rst
odoo_addons/openeducat_erp/static/description/openeducat_logo.png
odoo_addons/openeducat_erp/static/description/enrollment.png
odoo_addons/openeducat_erp/static/description/blog.png
odoo_addons/openeducat_erp/static/description/faculty.png
odoo_addons/openeducat_erp/static/description/news.png
odoo_addons/openeducat_erp/static/description/openeducat_erp_banner.jpg
odoo_addons/openeducat_erp/static/description/assignment.png
odoo_addons/openeducat_erp/static/description/exam.png
odoo_addons/openeducat_erp/static/description/dashboard.png
odoo_addons/openeducat_erp/static/description/library.png
odoo_addons/openeducat_erp/static/description/attendance.png
odoo_addons/openeducat_erp/static/description/reporting.png
odoo_addons/openeducat_erp/static/description/student.png
odoo_addons/openeducat_erp/static/description/index.html
odoo_addons/openeducat_erp/static/description/timetable.png
odoo_addons/openeducat_erp/static/description/class.png
odoo_addons/openeducat_erp/static/description/result.png
odoo_addons/openeducat_erp/static/description/financial.png
odoo_addons/openeducat_erp/static/description/events.png
odoo_addons/openeducat_erp/static/description/icon.png
odoo9_addon_openeducat_erp-9.0.2.4.0.dist-info/top_level.txt
odoo9_addon_openeducat_erp-9.0.2.4.0.dist-info/WHEEL
odoo9_addon_openeducat_erp-9.0.2.4.0.dist-info/RECORD
odoo9_addon_openeducat_erp-9.0.2.4.0.dist-info/metadata.json
odoo9_addon_openeducat_erp-9.0.2.4.0.dist-info/DESCRIPTION.rst
odoo9_addon_openeducat_erp-9.0.2.4.0.dist-info/METADATA
odoo9_addon_openeducat_erp-9.0.2.4.0.dist-info/namespace_packages.txt
