Metadata-Version: 2.0
Name: odoo9-addon-openeducat-erp
Version: 9.0.2.4.0
Summary: Manage Students, Faculties and Education Institute
Home-page: http://www.openeducat.org
Author: UNKNOWN
Author-email: UNKNOWN
License: UNKNOWN
Platform: UNKNOWN
Requires-Dist: odoo (<9.1a,>=9.0a)
Requires-Dist: odoo9-addon-openeducat-achievement
Requires-Dist: odoo9-addon-openeducat-activity
Requires-Dist: odoo9-addon-openeducat-admission
Requires-Dist: odoo9-addon-openeducat-alumni
Requires-Dist: odoo9-addon-openeducat-assignment
Requires-Dist: odoo9-addon-openeducat-attendance
Requires-Dist: odoo9-addon-openeducat-exam
Requires-Dist: odoo9-addon-openeducat-health
Requires-Dist: odoo9-addon-openeducat-hostel
Requires-Dist: odoo9-addon-openeducat-library
Requires-Dist: odoo9-addon-openeducat-parent
Requires-Dist: odoo9-addon-openeducat-placement
Requires-Dist: odoo9-addon-openeducat-scholarship
Requires-Dist: odoo9-addon-openeducat-timetable
Requires-Dist: odoo9-addon-openeducat-transportation
Classifier: Programming Language :: Python :: 2.7
Classifier: Framework :: Odoo
